cartridge_downloads/cartridge_override_urls.py
cartridge_downloads/checkout.py
cartridge_downloads/page_processors.py
cartridge_downloads/__init__.py
cartridge_downloads/signals.py
cartridge_downloads/utils.py
cartridge_downloads/models.py
cartridge_downloads/admin.py
cartridge_downloads/apps.py
cartridge_downloads/urls.py
cartridge_downloads/templates/email/order_receipt.html
cartridge_downloads/templates/email/form_response.html
cartridge_downloads/templates/email/order_receipt.txt
cartridge_downloads/templates/email/form_response.txt
cartridge_downloads/templates/shop/complete.html
cartridge_downloads/templates/shop/downloads/index.html
cartridge_downloads/views/override_cartridge.py
cartridge_downloads/views/__init__.py
cartridge_downloads/views/override_filebrowser.py
cartridge_downloads/views/views.py
cartridge_downloads/migrations/0001_initial.py
cartridge_downloads/migrations/__init__.py
cartridge_downloads/migrations/0002_v0_3_0.py
cartridge_downloads/templatetags/downloads.py
cartridge_downloads/templatetags/__init__.py
cartridge_downloads-0.3.9.dist-info/DESCRIPTION.rst
cartridge_downloads-0.3.9.dist-info/top_level.txt
cartridge_downloads-0.3.9.dist-info/RECORD
cartridge_downloads-0.3.9.dist-info/WHEEL
cartridge_downloads-0.3.9.dist-info/METADATA
cartridge_downloads-0.3.9.dist-info/metadata.json
